lazy_property/__init__.py
lazy_property-0.0.1.dist-info/DESCRIPTION.rst
lazy_property-0.0.1.dist-info/METADATA
lazy_property-0.0.1.dist-info/RECORD
lazy_property-0.0.1.dist-info/WHEEL
lazy_property-0.0.1.dist-info/metadata.json
lazy_property-0.0.1.dist-info/top_level.txt
