Metadata-Version: 1.0
Name: lazy-property
Version: 0.0.1
Summary: Makes properties lazy (ie evaluated only when called)
Home-page: https://github.com/jackmaney/lazy-property.git
Author: Jack Maney
Author-email: jackmaney@gmail.com
License: MIT
Platform: UNKNOWN
